Metadata-Version: 1.0
Name: davis-distributions
Version: 1.0.0
Summary: Udacity AWS Machine Learning Fundamentals Course
Home-page: https://github.com/davispeixoto/udacity-aws-ml
Author: Davis Peixoto
Author-email: davis.peixoto@gmail.com
License: UNKNOWN
Platform: UNKNOWN
